gprofiler/__init__.py
gprofiler/gprofiler.py
gprofiler/version.py
gprofiler_official-1.0.0.dist-info/LICENSE.txt
gprofiler_official-1.0.0.dist-info/METADATA
gprofiler_official-1.0.0.dist-info/WHEEL
gprofiler_official-1.0.0.dist-info/top_level.txt
gprofiler_official-1.0.0.dist-info/RECORD
