Metadata-Version: 2.1
Name: gprofiler-official
Version: 1.0.0
Summary: Functional enrichment analysis and more via the g:Profiler toolkit
Home-page: https://biit.cs.ut.ee/gprofiler/
Author: Uku Raudvere
Author-email: biit.support@ut.ee
License: UNKNOWN
Platform: UNKNOWN
Classifier: Development Status :: 4 - Beta
Classifier: Intended Audience :: Science/Research
Classifier: License :: OSI Approved :: BSD License
Classifier: Natural Language :: English
Classifier: Operating System :: OS Independent
Classifier: Programming Language :: Python :: 3
Classifier: Topic :: Scientific/Engineering :: Bio-Informatics
